aiotgm/__init__.py
aiotgm/api.py
aiotgm/client.py
aiotgm/constants.py
aiotgm/logging.py
aiotgm/types.py
aiotgm/update_manager.py
aiotgm/utils.py
aiotgm-0.5.4.dist-info/LICENSE
aiotgm-0.5.4.dist-info/METADATA
aiotgm-0.5.4.dist-info/WHEEL
aiotgm-0.5.4.dist-info/top_level.txt
aiotgm-0.5.4.dist-info/RECORD
